iamai/adapter/apscheduler/__init__.py
iamai/adapter/apscheduler/config.py
iamai/adapter/apscheduler/event.py
iamai_adapter_apscheduler-3.3.2.dist-info/METADATA
iamai_adapter_apscheduler-3.3.2.dist-info/WHEEL
iamai_adapter_apscheduler-3.3.2.dist-info/licenses/LICENSE
iamai_adapter_apscheduler-3.3.2.dist-info/RECORD
