Metadata-Version: 2.1
Name: iamai-adapter-apscheduler
Version: 3.3.2
Summary: apscheduler adapter for iamai.
Project-URL: Homepage, https://iamai.retrofor.space/
Project-URL: Documentation, https://iamai.retrofor.space/
Project-URL: Repository, https://github.com/retrofor/iamai
Project-URL: Changelog, https://iamai.retrofor.space/changelog.html
Author-email: 简律纯 <i@jyunko.cn>
License: MIT
License-File: LICENSE
Keywords: bot,chatbot,cqhttp,ontbot,qq
Classifier: Development Status :: 3 - Alpha
Classifier: Framework :: AsyncIO
Classifier: Framework :: Robot Framework
Classifier: Framework :: Robot Framework :: Library
Classifier: License :: OSI Approved :: MIT License
Classifier: Operating System :: OS Independent
Classifier: Programming Language :: Python :: 3
Classifier: Topic :: Communications :: Chat
Requires-Python: >=3.8
Requires-Dist: iamai>=3.3
